sparkverse/__init__.py
sparkverse/external_data.py
sparkverse/player.py
sparkverse/sensor.py
sparkverse/simulator.py
sparkverse/utils.py
sparkverse/components/__init__.py
sparkverse/components/log.py
sparkverse/components/video.py
sparkverse/data/Cropps1.png
sparkverse/data/Cropps2.png
sparkverse/data/LaneKeeper1.png
sparkverse/data/LaneKeeper2.png
sparkverse/data/LaneKeeper3.png
sparkverse/data/LineFollower1.png
sparkverse/data/LineFollower2.png
sparkverse/data/logo.png
sparkverse/data/logo1.png
sparkverse/data/player.png
sparkverse/gui/__init__.py
sparkverse/gui/help_bar.py
sparkverse/gui/sensor_bar.py
sparkverse-0.0.6.dist-info/LICENSE
sparkverse-0.0.6.dist-info/METADATA
sparkverse-0.0.6.dist-info/WHEEL
sparkverse-0.0.6.dist-info/entry_points.txt
sparkverse-0.0.6.dist-info/top_level.txt
sparkverse-0.0.6.dist-info/RECORD
