Metadata-Version: 2.1
Name: sparkverse
Version: 0.0.6
Summary: Simple python3 simulator for advance driving systems
Home-page: https://github.com/Amporu/SparkVerse
Author: Tucudean Adrian-Ionut
Author-email: Tucudean.Adrian.Ionut0@gmail.com
License: MIT
Keywords: Simulator computer vision Advanced Driving
Classifier: Development Status :: 1 - Planning
Classifier: Intended Audience :: Developers
Classifier: Programming Language :: Python :: 3
Classifier: Operating System :: Unix
Classifier: Operating System :: MacOS :: MacOS X
Classifier: Operating System :: Microsoft :: Windows
License-File: LICENSE
Requires-Dist: opencv-python
Requires-Dist: pygame
